Metadata-Version: 2.1
Name: cbtpkg
Version: 0.0.24
Summary: Mock package that allows you to find celebrity by date of birth
Home-page: https://github.com/TyW-98/standard-project-structure.git
Author: TYW-98
License: MIT
Classifier: Programming Language :: Python :: 3.7
License-File: LICENSE
